<?xml version="1.0" encoding="utf-8"?>
<StructureDefinition xmlns="http://hl7.org/fhir">
  <id value="Device-PeriodImplantation" />
  <meta>
    <lastUpdated value="2022-07-25T17:42:01.4253448+00:00" />
  </meta>
  <url value="https://annuaire.sante.gouv.fr/fhir/StructureDefinition/Device-PeriodImplantation" />
  <version value="0.3" />
  <name value="DevicePeriodImplantation" />
  <status value="draft" />
  <publisher value="ANS" />
  <contact>
    <name value="monserviceclient.annuaire@esante.gouv.fr" />
  </contact>
  <fhirVersion value="4.0.1" />
  <mapping>
    <identity value="rim" />
    <uri value="http://hl7.org/v3" />
    <name value="RIM Mapping" />
  </mapping>
  <kind value="complex-type" />
  <abstract value="false" />
  <context>
    <type value="element" />
    <expression value="Device" />
  </context>
  <type value="Extension" />
  <baseDefinition value="http://hl7.org/fhir/StructureDefinition/Extension" />
  <derivation value="constraint" />
  <differential>
    <element id="Extension">
      <path value="Extension" />
      <short value="Dates de mise en oeuvre de l'EML" />
    </element>
    <element id="Extension.url">
      <path value="Extension.url" />
      <fixedUri value="https://annuaire.sante.gouv.fr/fhir/StructureDefinition/Device-PeriodImplantation" />
    </element>
    <element id="Extension.value[x]">
      <path value="Extension.value[x]" />
      <type>
        <code value="Period" />
      </type>
    </element>
    <element id="Extension.value[x].start">
      <path value="Extension.value[x].start" />
      <short value="Date de mise en œuvre" />
    </element>
    <element id="Extension.value[x].end">
      <path value="Extension.value[x].end" />
      <short value="Date de fin de mise en œuvre" />
    </element>
  </differential>
</StructureDefinition>
